{
  "extraction_date": "2025-10-02T11:55:53.380711",
  "year": 2024,
  "article_type": "comparison",
  "publication_date": "2024-01-02",
  "article_data": {
    "doi": "10.1186/s12889-023-17588-2",
    "title": "Are physical activity and sleep associated with emotional self-regulation in toddlers? a cross-sectional study",
    "article_number": "61",
    "publication_date": "2024-01-02",
    "volume": "24",
    "issue": "1",
    "journal": "BMC Public Health",
    "issn": "1471-2458",
    "authors": [
      "Abhigale F. L. D’Cruz",
      "Katherine L. Downing",
      "Emma Sciberras",
      "Kylie D. Hesketh"
    ]
  },
  "article_index": 59,
  "citation_counts": {
    "semantic": {
      "client_name": "Semantic Scholar",
      "citation_count": 5,
      "retrieved_at": "2025-10-03T14:18:16.774406"
    },
    "crossref": {
      "client_name": "Crossref",
      "citation_count": 5,
      "retrieved_at": "2025-10-03T14:18:18.340229"
    },
    "opencitations": {
      "client_name": "OpenCitations",
      "citation_count": 4,
      "retrieved_at": "2025-10-03T14:18:19.667361"
    },
    "nature_scraper": {
      "client_name": "Nature Web Scraper",
      "citation_count": 3,
      "retrieved_at": "2025-10-03T21:30:54.704649"
    },
    "last_updated": "2025-10-03T21:30:54.704695"
  }
}