{
  "extraction_date": "2025-10-02T11:49:38.749507",
  "year": 2014,
  "article_type": "comparison",
  "publication_date": "2014-01-02",
  "article_data": {
    "doi": "10.1186/1471-2458-14-S1-P9",
    "title": "Pattern of outpatient utilisation and cost for patients under the Universal Coverage",
    "article_number": "P9",
    "publication_date": "2014-01-29",
    "volume": "14",
    "issue": "Suppl 1",
    "journal": "BMC Public Health",
    "issn": "1471-2458",
    "authors": [
      "Kanet Sumputtanon",
      "Nilawan Upakdee",
      "Pudtan Phanthunane",
      "Supasit Pannarunothai"
    ]
  },
  "article_index": 71,
  "citation_counts": {
    "semantic": {
      "client_name": "Semantic Scholar",
      "citation_count": 1,
      "retrieved_at": "2025-10-03T12:59:56.732349"
    },
    "crossref": {
      "client_name": "Crossref",
      "citation_count": 0,
      "retrieved_at": "2025-10-03T12:59:58.292440"
    },
    "opencitations": {
      "client_name": "OpenCitations",
      "citation_count": 0,
      "retrieved_at": "2025-10-03T12:59:59.529389"
    },
    "nature_scraper": {
      "client_name": "Nature Web Scraper",
      "citation_count": null,
      "retrieved_at": "2025-10-03T21:02:43.890892"
    },
    "last_updated": "2025-10-03T21:02:43.891083"
  }
}