{
  "extraction_date": "2025-10-02T11:55:04.655772",
  "year": 2021,
  "article_type": "comparison",
  "publication_date": "2021-01-02",
  "article_data": {
    "doi": "10.1186/s12889-020-10033-8",
    "title": "Intersection of HIV and Anemia in women of reproductive age: a 10-year analysis of three Zimbabwe demographic health surveys, 2005–2015",
    "article_number": "41",
    "publication_date": "2021-01-06",
    "volume": "21",
    "issue": "1",
    "journal": "BMC Public Health",
    "issn": "1471-2458",
    "authors": [
      "Philimon N. Gona",
      "Clara M. Gona",
      "Vasco Chikwasha",
      "Clara Haruzivishe",
      "Chabila C. Mapoma",
      "Sowmya R. Rao"
    ]
  },
  "article_index": 226,
  "citation_counts": {
    "semantic": {
      "client_name": "Semantic Scholar",
      "citation_count": 9,
      "retrieved_at": "2025-10-03T13:51:23.102381"
    },
    "crossref": {
      "client_name": "Crossref",
      "citation_count": 8,
      "retrieved_at": "2025-10-03T13:51:24.673738"
    },
    "opencitations": {
      "client_name": "OpenCitations",
      "citation_count": 6,
      "retrieved_at": "2025-10-03T13:51:25.980498"
    },
    "nature_scraper": {
      "client_name": "Nature Web Scraper",
      "citation_count": 8,
      "retrieved_at": "2025-10-03T21:21:28.125805"
    },
    "last_updated": "2025-10-03T21:21:28.125993"
  }
}