{
  "extraction_date": "2025-10-02T11:39:54.533855",
  "year": 2025,
  "article_type": "comparison",
  "publication_date": "2025-01-02",
  "article_data": {
    "doi": "10.1038/s41467-024-55711-y",
    "title": "A noncanonical role of ",
    "article_number": "155",
    "publication_date": "2025-01-02",
    "volume": "16",
    "issue": "1",
    "journal": "Nature Communications",
    "issn": "2041-1723",
    "authors": [
      "Jianjian Li",
      "Shuyang Xu",
      "Zicong Liu",
      "Liuyi Yang",
      "Zhe Ming",
      "Rui Zhang",
      "Wenjuan Zhao",
      "Huipai Peng",
      "Jeffrey J. Quinn",
      "Manyin Wu",
      "Yushan Geng",
      "Yuying Zhang",
      "Jiazhi He",
      "Minghai Chen",
      "Nan Li",
      "Ning-Yi Shao",
      "Qing Ma"
    ]
  },
  "article_index": 148,
  "citation_counts": {
    "semantic": {
      "client_name": "Semantic Scholar",
      "citation_count": 3,
      "retrieved_at": "2025-10-03T19:25:15.278289"
    },
    "crossref": {
      "client_name": "Crossref",
      "citation_count": 4,
      "retrieved_at": "2025-10-03T19:25:16.796850"
    },
    "opencitations": {
      "client_name": "OpenCitations",
      "citation_count": 0,
      "retrieved_at": "2025-10-03T19:25:17.968150"
    },
    "nature_scraper": {
      "client_name": "Nature Web Scraper",
      "citation_count": 4,
      "retrieved_at": "2025-10-03T23:22:32.416386"
    },
    "last_updated": "2025-10-03T23:22:32.416584"
  }
}