{
  "extraction_date": "2025-10-02T11:43:47.858279",
  "year": 2024,
  "article_type": "comparison",
  "publication_date": "2024-01-02",
  "article_data": {
    "doi": "10.1038/s41598-023-50699-9",
    "title": "Variability in proximate composition, phytochemical traits and antioxidant properties of Iranian agro-ecotypic populations of fenugreek (",
    "article_number": "87",
    "publication_date": "2024-01-02",
    "volume": "14",
    "issue": "1",
    "journal": "Scientific Reports",
    "issn": "2045-2322",
    "authors": [
      "Ziba Bakhtiar",
      "Mohammadreza Hassandokht",
      "Mohammad Reza Naghavi",
      "Mohammad Hossein Mirjalili"
    ]
  },
  "article_index": 242,
  "citation_counts": {
    "semantic": {
      "client_name": "Semantic Scholar",
      "citation_count": 10,
      "retrieved_at": "2025-10-03T15:57:53.430644"
    },
    "crossref": {
      "client_name": "Crossref",
      "citation_count": 9,
      "retrieved_at": "2025-10-03T15:57:54.935633"
    },
    "opencitations": {
      "client_name": "OpenCitations",
      "citation_count": 7,
      "retrieved_at": "2025-10-03T15:57:56.200874"
    },
    "nature_scraper": {
      "client_name": "Nature Web Scraper",
      "citation_count": 9,
      "retrieved_at": "2025-10-03T22:10:44.826220"
    },
    "last_updated": "2025-10-03T22:10:44.826309"
  }
}