{
  "extraction_date": "2025-10-02T11:39:54.539333",
  "year": 2025,
  "article_type": "comparison",
  "publication_date": "2025-01-02",
  "article_data": {
    "doi": "10.1038/s41467-024-55354-z",
    "title": "Entanglement microscopy and tomography in many-body systems",
    "article_number": "96",
    "publication_date": "2025-01-02",
    "volume": "16",
    "issue": "1",
    "journal": "Nature Communications",
    "issn": "2041-1723",
    "authors": [
      "Ting-Tung Wang",
      "Menghan Song",
      "Liuke Lyu",
      "William Witczak-Krempa",
      "Zi Yang Meng"
    ]
  },
  "article_index": 199,
  "citation_counts": {
    "semantic": {
      "client_name": "Semantic Scholar",
      "citation_count": 14,
      "retrieved_at": "2025-10-03T19:29:01.887053"
    },
    "crossref": {
      "client_name": "Crossref",
      "citation_count": 7,
      "retrieved_at": "2025-10-03T19:29:03.403223"
    },
    "opencitations": {
      "client_name": "OpenCitations",
      "citation_count": 0,
      "retrieved_at": "2025-10-03T19:29:04.540866"
    },
    "nature_scraper": {
      "client_name": "Nature Web Scraper",
      "citation_count": 8,
      "retrieved_at": "2025-10-03T23:23:46.364717"
    },
    "last_updated": "2025-10-03T23:23:46.364905"
  }
}