{
  "extraction_date": "2025-10-02T11:45:29.392969",
  "year": 2025,
  "article_type": "comparison",
  "publication_date": "2025-01-02",
  "article_data": {
    "doi": "10.1038/s41598-024-84757-7",
    "title": "Effect of ambient O",
    "article_number": "449",
    "publication_date": "2025-01-02",
    "volume": "15",
    "issue": "1",
    "journal": "Scientific Reports",
    "issn": "2045-2322",
    "authors": [
      "Yuhan Zhao",
      "Yuxia Ma",
      "Zongrui Liu",
      "Ziyue Wan",
      "Haoran Jiao",
      "Fengliu Feng",
      "Bowen Cheng"
    ]
  },
  "article_index": 403,
  "citation_counts": {
    "semantic": {
      "client_name": "Semantic Scholar",
      "citation_count": 3,
      "retrieved_at": "2025-10-03T16:21:41.453157"
    },
    "crossref": {
      "client_name": "Crossref",
      "citation_count": 3,
      "retrieved_at": "2025-10-03T16:21:43.022699"
    },
    "opencitations": {
      "client_name": "OpenCitations",
      "citation_count": 0,
      "retrieved_at": "2025-10-07T09:50:02.288508"
    },
    "nature_scraper": {
      "client_name": "Nature Web Scraper",
      "citation_count": 3,
      "retrieved_at": "2025-10-03T22:19:24.732192"
    },
    "last_updated": "2025-10-07T09:50:02.288720"
  }
}