{
  "extraction_date": "2025-10-02T11:45:29.342427",
  "year": 2025,
  "article_type": "comparison",
  "publication_date": "2025-01-02",
  "article_data": {
    "doi": "10.1038/s41598-024-84783-5",
    "title": "Fault diagnosis of rotating parts integrating transfer learning and ConvNeXt model",
    "article_number": "190",
    "publication_date": "2025-01-02",
    "volume": "15",
    "issue": "1",
    "journal": "Scientific Reports",
    "issn": "2045-2322",
    "authors": [
      "Zhikai Xing",
      "Yongbao Liu",
      "Qiang Wang",
      "Junqiang Fu"
    ]
  },
  "article_index": 10,
  "citation_counts": {
    "semantic": {
      "client_name": "Semantic Scholar",
      "citation_count": 5,
      "retrieved_at": "2025-10-03T16:30:59.039463"
    },
    "crossref": {
      "client_name": "Crossref",
      "citation_count": 6,
      "retrieved_at": "2025-10-03T16:31:00.638364"
    },
    "opencitations": {
      "client_name": "OpenCitations",
      "citation_count": 0,
      "retrieved_at": "2025-10-07T09:51:52.559095"
    },
    "nature_scraper": {
      "client_name": "Nature Web Scraper",
      "citation_count": 7,
      "retrieved_at": "2025-10-03T22:22:37.344714"
    },
    "last_updated": "2025-10-07T09:51:52.559299"
  }
}