{
  "extraction_date": "2025-10-02T11:45:29.396692",
  "year": 2025,
  "article_type": "comparison",
  "publication_date": "2025-01-02",
  "article_data": {
    "doi": "10.1038/s41598-024-75408-y",
    "title": "Factors associated with vaccine default in Southern Ghana based on data from the RTSS malaria vaccine trial in Cape Coast",
    "article_number": "251",
    "publication_date": "2025-01-02",
    "volume": "15",
    "issue": "1",
    "journal": "Scientific Reports",
    "issn": "2045-2322",
    "authors": [
      "Vincent Bio Bediako",
      "Josephine Akua Ackah",
      "Theophilus Junior Yankey",
      "Joshua Okyere",
      "Emmanuella Acheampong",
      "Bernard Afriyie Owusu",
      "Wonder Agbemavi",
      "Adanna Uloaku Nwameme",
      "Edward Mberu Kamau",
      "Emmanuel Asampong"
    ]
  },
  "article_index": 437,
  "citation_counts": {
    "semantic": {
      "client_name": "Semantic Scholar",
      "citation_count": 3,
      "retrieved_at": "2025-10-03T16:38:15.062158"
    },
    "crossref": {
      "client_name": "Crossref",
      "citation_count": 2,
      "retrieved_at": "2025-10-03T16:38:16.734278"
    },
    "opencitations": {
      "client_name": "OpenCitations",
      "citation_count": 0,
      "retrieved_at": "2025-10-03T16:38:17.915203"
    },
    "nature_scraper": {
      "client_name": "Nature Web Scraper",
      "citation_count": 3,
      "retrieved_at": "2025-10-03T22:25:11.594183"
    },
    "last_updated": "2025-10-03T22:25:11.594417"
  }
}