{
  "extraction_date": "2025-10-02T11:54:20.687441",
  "year": 2020,
  "article_type": "comparison",
  "publication_date": "2020-01-02",
  "article_data": {
    "doi": "10.1186/s12889-019-8127-9",
    "title": "Understanding the healthcare experiences and needs of African immigrants in the United States: a scoping review",
    "article_number": "27",
    "publication_date": "2020-01-08",
    "volume": "20",
    "issue": "1",
    "journal": "BMC Public Health",
    "issn": "1471-2458",
    "authors": [
      "Ogbonnaya I. Omenka",
      "Dennis P. Watson",
      "Hugh C. Hendrie"
    ]
  },
  "article_index": 146,
  "citation_counts": {
    "semantic": {
      "client_name": "Semantic Scholar",
      "citation_count": 107,
      "retrieved_at": "2025-10-03T13:39:50.875081"
    },
    "crossref": {
      "client_name": "Crossref",
      "citation_count": 113,
      "retrieved_at": "2025-10-03T13:39:52.470984"
    },
    "opencitations": {
      "client_name": "OpenCitations",
      "citation_count": 64,
      "retrieved_at": "2025-10-03T13:39:53.883507"
    },
    "nature_scraper": {
      "client_name": "Nature Web Scraper",
      "citation_count": 128,
      "retrieved_at": "2025-10-03T21:17:20.650866"
    },
    "last_updated": "2025-10-03T21:17:20.651059"
  }
}