{
  "extraction_date": "2025-10-02T11:48:52.531736",
  "year": 2010,
  "article_type": "comparison",
  "publication_date": "2010-01-01",
  "article_data": {
    "doi": "10.1186/1471-2458-10-6",
    "title": "Health-related quality of life among individuals with long-standing spinal cord injury: a comparative study of veterans and non-veterans",
    "article_number": "6",
    "publication_date": "2010-01-05",
    "volume": "10",
    "issue": "1",
    "journal": "BMC Public Health",
    "issn": "1471-2458",
    "authors": [
      "Soheil Saadat",
      "Masoud Javadi",
      "Baharak Sabet Divshali",
      "Amir Hussein Tavakoli",
      "Seyed Mohammad Ghodsi",
      "Ali Montazeri",
      "Vafa Rahimi-Movaghar"
    ]
  },
  "article_index": 43,
  "citation_counts": {
    "semantic": {
      "client_name": "Semantic Scholar",
      "citation_count": 65,
      "retrieved_at": "2025-10-03T12:39:59.682930"
    },
    "crossref": {
      "client_name": "Crossref",
      "citation_count": 23,
      "retrieved_at": "2025-10-03T12:40:01.201520"
    },
    "opencitations": {
      "client_name": "OpenCitations",
      "citation_count": 36,
      "retrieved_at": "2025-10-03T12:40:02.459747"
    },
    "nature_scraper": {
      "client_name": "Nature Web Scraper",
      "citation_count": 35,
      "retrieved_at": "2025-10-03T20:55:30.689975"
    },
    "last_updated": "2025-10-03T20:55:30.690025"
  }
}