{
  "extraction_date": "2025-10-02T11:48:52.528559",
  "year": 2010,
  "article_type": "comparison",
  "publication_date": "2010-01-01",
  "article_data": {
    "doi": "10.1186/1471-2458-10-42",
    "title": "Differences in school environment, school policy and actions regarding overweight prevention between Dutch schools. A nationwide survey",
    "article_number": "42",
    "publication_date": "2010-01-28",
    "volume": "10",
    "issue": "1",
    "journal": "BMC Public Health",
    "issn": "1471-2458",
    "authors": [
      "Salome Scholtens",
      "Lideke Middelbeek",
      "Suzanne I Rutz",
      "Goof Buijs",
      "Wanda JE Bemelmans"
    ]
  },
  "article_index": 24,
  "citation_counts": {
    "semantic": {
      "client_name": "Semantic Scholar",
      "citation_count": 17,
      "retrieved_at": "2025-10-03T12:41:25.351896"
    },
    "crossref": {
      "client_name": "Crossref",
      "citation_count": 15,
      "retrieved_at": "2025-10-03T12:41:26.922445"
    },
    "opencitations": {
      "client_name": "OpenCitations",
      "citation_count": 16,
      "retrieved_at": "2025-10-03T12:41:28.163948"
    },
    "nature_scraper": {
      "client_name": "Nature Web Scraper",
      "citation_count": 16,
      "retrieved_at": "2025-10-03T20:56:02.694085"
    },
    "last_updated": "2025-10-03T20:56:02.694273"
  }
}