{
  "extraction_date": "2025-10-02T11:48:07.958279",
  "year": 2005,
  "article_type": "comparison",
  "publication_date": "2005-01-03",
  "article_data": {
    "doi": "10.1186/1471-2458-5-100",
    "title": "Birth outcomes in Colorado's undocumented immigrant population",
    "article_number": "100",
    "publication_date": "2005-10-04",
    "volume": "5",
    "issue": "1",
    "journal": "BMC Public Health",
    "issn": "1471-2458",
    "authors": [
      "Mary M Reed",
      "John M Westfall",
      "Caroline Bublitz",
      "Catherine Battaglia",
      "Alexandra Fickenscher"
    ]
  },
  "article_index": 41,
  "citation_counts": {
    "semantic": {
      "client_name": "Semantic Scholar",
      "citation_count": 108,
      "retrieved_at": "2025-10-03T12:24:04.368384"
    },
    "crossref": {
      "client_name": "Crossref",
      "citation_count": 73,
      "retrieved_at": "2025-10-03T12:24:05.903833"
    },
    "opencitations": {
      "client_name": "OpenCitations",
      "citation_count": 71,
      "retrieved_at": "2025-10-03T12:24:07.239026"
    },
    "nature_scraper": {
      "client_name": "Nature Web Scraper",
      "citation_count": 82,
      "retrieved_at": "2025-10-03T20:49:59.289746"
    },
    "last_updated": "2025-10-03T20:49:59.289951"
  }
}