{
  "extraction_date": "2025-10-02T11:38:03.628116",
  "year": 2022,
  "article_type": "comparison",
  "publication_date": "2022-01-04",
  "article_data": {
    "doi": "10.1038/s41467-022-28246-3",
    "title": "Tracking cryptic SARS-CoV-2 lineages detected in NYC wastewater",
    "article_number": "635",
    "publication_date": "2022-02-03",
    "volume": "13",
    "issue": "1",
    "journal": "Nature Communications",
    "issn": "2041-1723",
    "authors": [
      "Davida S. Smyth",
      "Monica Trujillo",
      "Devon A. Gregory",
      "Kristen Cheung",
      "Anna Gao",
      "Maddie Graham",
      "Yue Guan",
      "Caitlyn Guldenpfennig",
      "Irene Hoxie",
      "Sherin Kannoly",
      "Nanami Kubota",
      "Terri D. Lyddon",
      "Michelle Markman",
      "Clayton Rushford",
      "Kaung Myat San",
      "Geena Sompanya",
      "Fabrizio Spagnolo",
      "Reinier Suarez",
      "Emma Teixeiro",
      "Mark Daniels",
      "Marc C. Johnson",
      "John J. Dennehy"
    ]
  },
  "article_index": 39
}