{
  "extraction_date": "2025-10-02T11:38:03.713084",
  "year": 2022,
  "article_type": "comparison",
  "publication_date": "2022-01-04",
  "article_data": {
    "doi": "10.1038/s41467-022-28203-0",
    "title": "Divalent metal cations stimulate skeleton interoception for new bone formation in mouse injury models",
    "article_number": "535",
    "publication_date": "2022-01-27",
    "volume": "13",
    "issue": "1",
    "journal": "Nature Communications",
    "issn": "2041-1723",
    "authors": [
      "Wei Qiao",
      "Dayu Pan",
      "Yufeng Zheng",
      "Shuilin Wu",
      "Xuanyong Liu",
      "Zhuofan Chen",
      "Mei Wan",
      "Shiqin Feng",
      "Kenneth M. C. Cheung",
      "Kelvin W. K. Yeung",
      "Xu Cao"
    ]
  },
  "article_index": 184
}