{
  "extraction_date": "2025-10-02T11:38:03.744826",
  "year": 2022,
  "article_type": "comparison",
  "publication_date": "2022-01-04",
  "article_data": {
    "doi": "10.1038/s41467-021-27920-2",
    "title": "Structure and function of a family of tick-derived complement inhibitors targeting properdin",
    "article_number": "317",
    "publication_date": "2022-01-14",
    "volume": "13",
    "issue": "1",
    "journal": "Nature Communications",
    "issn": "2041-1723",
    "authors": [
      "Katharina Braunger",
      "Jiyoon Ahn",
      "Matthijs M. Jore",
      "Steven Johnson",
      "Terence T. L. Tang",
      "Dennis V. Pedersen",
      "Gregers R. Andersen",
      "Susan M. Lea"
    ]
  },
  "article_index": 420
}