{
  "extraction_date": "2025-10-02T11:55:04.645754",
  "year": 2021,
  "article_type": "comparison",
  "publication_date": "2021-01-02",
  "article_data": {
    "doi": "10.1186/s12889-020-09893-x",
    "title": "Can adopting skin cancer preventive behaviors among seafarers be increased via a theory-based mobile phone-based text message intervention? A randomized clinical trial",
    "article_number": "134",
    "publication_date": "2021-01-14",
    "volume": "21",
    "issue": "1",
    "journal": "BMC Public Health",
    "issn": "1471-2458",
    "authors": [
      "Esmat Heydari",
      "Tahereh Dehdari",
      "Mahnaz Solhi"
    ]
  },
  "article_index": 129,
  "citation_counts": {
    "semantic": {
      "client_name": "Semantic Scholar",
      "citation_count": 10,
      "retrieved_at": "2025-10-03T13:41:58.419200"
    },
    "crossref": {
      "client_name": "Crossref",
      "citation_count": 11,
      "retrieved_at": "2025-10-03T13:41:59.967953"
    },
    "opencitations": {
      "client_name": "OpenCitations",
      "citation_count": 9,
      "retrieved_at": "2025-10-03T13:42:01.452191"
    },
    "nature_scraper": {
      "client_name": "Nature Web Scraper",
      "citation_count": 12,
      "retrieved_at": "2025-10-03T21:18:07.708509"
    },
    "last_updated": "2025-10-03T21:18:07.708705"
  }
}