{
  "extraction_date": "2025-10-02T11:38:03.709602",
  "year": 2022,
  "article_type": "comparison",
  "publication_date": "2022-01-04",
  "article_data": {
    "doi": "10.1038/s41467-022-28165-3",
    "title": "Carbohydrate-aromatic interface and molecular architecture of lignocellulose",
    "article_number": "538",
    "publication_date": "2022-01-27",
    "volume": "13",
    "issue": "1",
    "journal": "Nature Communications",
    "issn": "2041-1723",
    "authors": [
      "Alex Kirui",
      "Wancheng Zhao",
      "Fabien Deligey",
      "Hui Yang",
      "Xue Kang",
      "Frederic Mentink-Vigier",
      "Tuo Wang"
    ]
  },
  "article_index": 164
}