{
  "extraction_date": "2025-10-02T11:38:03.767356",
  "year": 2022,
  "article_type": "comparison",
  "publication_date": "2022-01-04",
  "article_data": {
    "doi": "10.1038/s41467-021-27750-2",
    "title": "Yeast-derived nanoparticles remodel the immunosuppressive microenvironment in tumor and tumor-draining lymph nodes to suppress tumor growth",
    "article_number": "110",
    "publication_date": "2022-01-10",
    "volume": "13",
    "issue": "1",
    "journal": "Nature Communications",
    "issn": "2041-1723",
    "authors": [
      "Jialu Xu",
      "Qingle Ma",
      "Yue Zhang",
      "Ziying Fei",
      "Yifei Sun",
      "Qin Fan",
      "Bo Liu",
      "Jinyu Bai",
      "Yue Yu",
      "Jianhong Chu",
      "Jingrun Chen",
      "Chao Wang"
    ]
  },
  "article_index": 620
}