{
  "extraction_date": "2025-10-02T11:45:29.347503",
  "year": 2025,
  "article_type": "comparison",
  "publication_date": "2025-01-02",
  "article_data": {
    "doi": "10.1038/s41598-024-83418-z",
    "title": "Development and validation of a prognostic nomogram model for severe osteomyelitis patients",
    "article_number": "318",
    "publication_date": "2025-01-02",
    "volume": "15",
    "issue": "1",
    "journal": "Scientific Reports",
    "issn": "2045-2322",
    "authors": [
      "Yunlong Liu",
      "Yan Zheng",
      "Sheng Ding"
    ]
  },
  "article_index": 58,
  "citation_counts": {
    "semantic": {
      "client_name": "Semantic Scholar",
      "citation_count": null,
      "retrieved_at": "2025-10-03T16:42:11.893306"
    },
    "crossref": {
      "client_name": "Crossref",
      "citation_count": 0,
      "retrieved_at": "2025-10-03T16:42:13.406995"
    },
    "opencitations": {
      "client_name": "OpenCitations",
      "citation_count": 0,
      "retrieved_at": "2025-10-03T16:42:14.578254"
    },
    "nature_scraper": {
      "client_name": "Nature Web Scraper",
      "citation_count": null,
      "retrieved_at": "2025-10-03T22:26:39.955612"
    },
    "last_updated": "2025-10-03T22:26:39.955658"
  }
}