{
  "extraction_date": "2025-10-02T11:45:29.395502",
  "year": 2025,
  "article_type": "comparison",
  "publication_date": "2025-01-02",
  "article_data": {
    "doi": "10.1038/s41598-024-84182-w",
    "title": "Machine learning-based technique for gain prediction of mm-wave miniaturized 5G MIMO slotted antenna array with high isolation characteristics",
    "article_number": "276",
    "publication_date": "2025-01-02",
    "volume": "15",
    "issue": "1",
    "journal": "Scientific Reports",
    "issn": "2045-2322",
    "authors": [
      "Md. Ashraful Haque",
      "Jamal Hossain Nirob",
      "Kamal Hossain Nahin",
      "Noorlindawaty Md Jizat",
      "M. A. Zakariya",
      "Redwan A. Ananta",
      "Wazie M. Abdulkawi",
      "Khaled Aljaloud",
      "Samir Salem Al-Bawri"
    ]
  },
  "article_index": 426,
  "citation_counts": {
    "semantic": {
      "client_name": "Semantic Scholar",
      "citation_count": 20,
      "retrieved_at": "2025-10-03T17:04:23.814082"
    },
    "crossref": {
      "client_name": "Crossref",
      "citation_count": 18,
      "retrieved_at": "2025-10-03T17:04:25.356547"
    },
    "opencitations": {
      "client_name": "OpenCitations",
      "citation_count": 0,
      "retrieved_at": "2025-10-03T17:04:26.578314"
    },
    "nature_scraper": {
      "client_name": "Nature Web Scraper",
      "citation_count": 22,
      "retrieved_at": "2025-10-03T22:34:31.314129"
    },
    "last_updated": "2025-10-03T22:34:31.314316"
  }
}