{
  "extraction_date": "2025-10-02T11:34:46.728696",
  "year": 2019,
  "article_type": "comparison",
  "publication_date": "2019-01-02",
  "article_data": {
    "doi": "10.1038/s41467-018-07854-y",
    "title": "Author Correction: Memory formation and long-term maintenance of IL-7Rα",
    "article_number": "160",
    "publication_date": "2019-01-08",
    "volume": "10",
    "issue": "1",
    "journal": "Nature Communications",
    "issn": "2041-1723",
    "authors": [
      "Xianwei Wang",
      "Hui Peng",
      "Jingjing Cong",
      "Xuefu Wang",
      "Zhexiong Lian",
      "Haiming Wei",
      "Rui Sun",
      "Zhigang Tian"
    ]
  },
  "article_index": 473,
  "citation_counts": {
    "semantic": {
      "client_name": "Semantic Scholar",
      "citation_count": 2,
      "retrieved_at": "2025-10-03T17:49:28.223382"
    },
    "crossref": {
      "client_name": "Crossref",
      "citation_count": 1,
      "retrieved_at": "2025-10-03T17:49:29.791110"
    },
    "opencitations": {
      "client_name": "OpenCitations",
      "citation_count": 1,
      "retrieved_at": "2025-10-03T17:49:31.045823"
    },
    "nature_scraper": {
      "client_name": "Nature Web Scraper",
      "citation_count": 1,
      "retrieved_at": "2025-10-03T22:50:04.040612"
    },
    "last_updated": "2025-10-03T22:50:04.040680"
  }
}