{
  "extraction_date": "2025-10-02T11:34:46.719273",
  "year": 2019,
  "article_type": "comparison",
  "publication_date": "2019-01-02",
  "article_data": {
    "doi": "10.1038/s41467-018-08088-8",
    "title": "Pseudodoping of a metallic two-dimensional material by the supporting substrate",
    "article_number": "180",
    "publication_date": "2019-01-14",
    "volume": "10",
    "issue": "1",
    "journal": "Nature Communications",
    "issn": "2041-1723",
    "authors": [
      "Bin Shao",
      "Andreas Eich",
      "Charlotte Sanders",
      "Arlette S. Ngankeu",
      "Marco Bianchi",
      "Philip Hofmann",
      "Alexander A. Khajetoorians",
      "Tim O. Wehling"
    ]
  },
  "article_index": 385,
  "citation_counts": {
    "semantic": {
      "client_name": "Semantic Scholar",
      "citation_count": 52,
      "retrieved_at": "2025-10-03T17:10:34.300186"
    },
    "crossref": {
      "client_name": "Crossref",
      "citation_count": 37,
      "retrieved_at": "2025-10-03T17:10:35.876682"
    },
    "opencitations": {
      "client_name": "OpenCitations",
      "citation_count": 32,
      "retrieved_at": "2025-10-03T17:10:37.063490"
    },
    "nature_scraper": {
      "client_name": "Nature Web Scraper",
      "citation_count": 39,
      "retrieved_at": "2025-10-03T22:36:49.720163"
    },
    "last_updated": "2025-10-03T22:36:49.720385"
  }
}